Metadata-Version: 2.1
Name: novigi-airflow-custom-operators
Version: 1.0
Summary: Novigi Custom Airflow Operators
Home-page: UNKNOWN
Author: Novigi
Author-email: prasadi.jayakodi@novigi.com.au
License: MIT
Platform: UNKNOWN
License-File: LICENSE.txt
